rannet/__init__.py
rannet/dataloader.py
rannet/layers.py
rannet/optimizer.py
rannet/pretrain.py
rannet/ran.py
rannet/rannet.py
rannet/tokenizer.py
rannet/utils.py
rannet-0.3.1.dist-info/LICENSE
rannet-0.3.1.dist-info/METADATA
rannet-0.3.1.dist-info/WHEEL
rannet-0.3.1.dist-info/top_level.txt
rannet-0.3.1.dist-info/RECORD
