Metadata-Version: 2.1
Name: rannet
Version: 0.3.1
Summary: Recurrent Attention Networks
Author: sean lee
Author-email: xmlee97@gmail.com
Keywords: rannet
Classifier: Development Status :: 5 - Production/Stable
Classifier: Intended Audience :: Developers
Classifier: License :: OSI Approved :: BSD License
Classifier: Natural Language :: English
Classifier: Programming Language :: Python :: 3
Classifier: Programming Language :: Python :: 3.7
Classifier: Programming Language :: Python :: 3.8
Classifier: Programming Language :: Python :: 3.9
Classifier: Programming Language :: Python :: 3.10
Classifier: Programming Language :: Python :: 3.11
License-File: LICENSE
Requires-Dist: langml (==0.4.2)
Requires-Dist: tokenizers
Requires-Dist: numpy
